vehicle_detection_lib/__init__.py
vehicle_detection_lib/vehicle_detector.py
vehicle_detection_lib-0.1.dist-info/METADATA
vehicle_detection_lib-0.1.dist-info/WHEEL
vehicle_detection_lib-0.1.dist-info/top_level.txt
vehicle_detection_lib-0.1.dist-info/RECORD
