Metadata-Version: 2.1
Name: vehicle-detection-lib
Version: 0.1
Summary: A library for vehicle detection using yolo.
Home-page: UNKNOWN
Author: Wan Abdul Muiz
Author-email: wwanabdulmuiz@gmail.com
License: UNKNOWN
Platform: UNKNOWN
Requires-Dist: opencv-python (>=4.5.0)
Requires-Dist: torch (>=1.7.0)
Requires-Dist: ultralytics
